LICENSE
MANIFEST.in
setup.py
UPY.egg-info/PKG-INFO
UPY.egg-info/SOURCES.txt
UPY.egg-info/dependency_links.txt
UPY.egg-info/not-zip-safe
UPY.egg-info/requires.txt
UPY.egg-info/top_level.txt
upy/__init__.py
upy/admin.py
upy/fields.py
upy/forms.py
upy/mail.py
upy/models.py
upy/upy_conf.py
upy/utils.py
upy/widgets.py
upy/bin/upy
upy/bin/upy_project_set/uwsgi.ini
upy/bin/upy_project_set/uwsgi_unbit.ini
upy/bin/upy_project_set/project/manage.py
upy/bin/upy_project_set/project/project/__init__.py
upy/bin/upy_project_set/project/project/custom_urls.py
upy/bin/upy_project_set/project/project/django_wsgi.py
upy/bin/upy_project_set/project/project/local_settings.py
upy/bin/upy_project_set/project/project/settings.py
upy/bin/upy_project_set/project/project/urls.py
upy/bin/upy_project_set/static/upstream_errorpage.html
upy/contrib/__init__.py
upy/contrib/cked/AUTHORS
upy/contrib/cked/LICENSE
upy/contrib/cked/README.rst
upy/contrib/cked/__init__.py
upy/contrib/cked/default_settings.py
upy/contrib/cked/elFinder.py
upy/contrib/cked/fields.py
upy/contrib/cked/models.py
upy/contrib/cked/urls.py
upy/contrib/cked/views.py
upy/contrib/cked/widgets.py
upy/contrib/cked/static/cked/ckeditor/CHANGES.md
upy/contrib/cked/static/cked/ckeditor/LICENSE.md
upy/contrib/cked/static/cked/ckeditor/README.md
upy/contrib/cked/static/cked/ckeditor/build-config.js
upy/contrib/cked/static/cked/ckeditor/ckeditor.js
upy/contrib/cked/static/cked/ckeditor/config.js
upy/contrib/cked/static/cked/ckeditor/contents.css
upy/contrib/cked/static/cked/ckeditor/styles.js
upy/contrib/cked/static/cked/ckeditor/lang/af.js
upy/contrib/cked/static/cked/ckeditor/lang/ar.js
upy/contrib/cked/static/cked/ckeditor/lang/bg.js
upy/contrib/cked/static/cked/ckeditor/lang/bn.js
upy/contrib/cked/static/cked/ckeditor/lang/bs.js
upy/contrib/cked/static/cked/ckeditor/lang/ca.js
upy/contrib/cked/static/cked/ckeditor/lang/cs.js
upy/contrib/cked/static/cked/ckeditor/lang/cy.js
upy/contrib/cked/static/cked/ckeditor/lang/da.js
upy/contrib/cked/static/cked/ckeditor/lang/de.js
upy/contrib/cked/static/cked/ckeditor/lang/el.js
upy/contrib/cked/static/cked/ckeditor/lang/en-au.js
